{
  "title": "Datakeepers",
  "version": "2.1",
  "settings": {
    "pagenumber": 0,
    "editable": true,
    "fullscreenEnabled": false,
    "parameters": {}
  },
  "pages": [
    {
      "title": "Main Page",
      "reports": [
        {
          "title": "Hi there 👋",
          "query": "**This is Datakeepers dashboard!** \n \nProblem1: Given a country X, provide a list of airports operating in country X.\n\nProblem2: Given a number of stops X, provide a list of airlines having X stops.\n\nProblem3: Given a code share X for airlines, provide a list of airlines operating with code share X.\n\nProblem4: Given the option to display active airlines, provide a list of active airlines if selected.\nAirline aggregation feature:\n\nProblem5: Given the option to display the country or territory with the highest number of airports, provide the country or territory with the highest number of airports if selected.\n\nProblem6:Given a number of cities X, provide the top X cities with the most incoming and outgoing airlines.\nTrip recommendation feature:\n\nProblem 7: Given two cities X and Y, provide a list of routes connecting cities X and Y.\n\nProblem 8: Given two cities X and Y and a number of stops Z, provide a list of routes connecting\ncities X and Y with fewer than Z stops.\n\nProblem 9: Given a city X and number of stops Y, provide a list of cities that can be reached from X\nwithin Y stops.\n\nProblem 10: Given city X, provide the path distance from city x to reachable city y and list it in the order of the best paths\n\n",
          "width": 4,
          "height": 2,
          "x": 0,
          "y": 0,
          "type": "text",
          "selection": {},
          "settings": {}
        },
        {
          "title": "Problem1",
          "query": "MATCH (p:Airport) \nWHERE p.Country = \"Iceland\"\nRETURN p.AirportID, p.Name, p.City, p.Country\n\n",
          "width": 4,
          "height": 2,
          "x": 4,
          "y": 0,
          "type": "table",
          "selection": {},
          "settings": {
            "nodePositions": {}
          }
        },
        {
          "title": "Problem3",
          "query": "MATCH (o:Route)-[r:FLOWN_BY]->(l:Airline)\nWHERE o.AirlineID = l.AirlineID AND o.Codeshare = \"Y\"\nRETURN DISTINCT l.AirlineID, l.Name, o.Codeshare",
          "width": 5,
          "height": 2,
          "x": 0,
          "y": 2,
          "type": "table",
          "selection": {},
          "settings": {
            "nodePositions": {}
          }
        },
        {
          "title": "Problem4",
          "query": "MATCH (l:Airline)\nWHERE l.Active = \"N\"\nRETURN DISTINCT l.AirlineID, l.Name, l.Active\n\n",
          "width": 6,
          "height": 2,
          "x": 5,
          "y": 2,
          "type": "table",
          "selection": {},
          "settings": {
            "nodePositions": {}
          }
        },
        {
          "title": "Problem2",
          "query": "MATCH (o:Route)-[r:FLOWN_BY]->(l:Airline)\nWHERE o.AirlineID = l.AirlineID AND\n\to.Stops = 1\nRETURN DISTINCT l.AirlineID, l.Name, o.Stops\nORDER BY l.AirlineID\n\n\n",
          "width": 4,
          "height": 2,
          "x": 8,
          "y": 0,
          "type": "table",
          "selection": {},
          "settings": {
            "nodePositions": {}
          }
        },
        {
          "title": "Problem5",
          "query": "MATCH (p:Airport)\nRETURN p.Country, COUNT(*) as Count\nORDER BY Count DESC\nLIMIT 10\n",
          "width": 6,
          "height": 2,
          "x": 0,
          "y": 4,
          "type": "pie",
          "selection": {
            "index": "p.Country",
            "value": "Count",
            "key": "(none)"
          },
          "settings": {
            "colors": "paired",
            "legend": false,
            "sortByValue": true
          }
        },
        {
          "title": "Problem6",
          "query": "MATCH ()-[incoming]->(n)-[outgoing]->() \nWITH n, incoming, outgoing\nWHERE n.City IS NOT NULL\nRETURN n.City, COUNT(DISTINCT incoming) AS Incoming, COUNT(DISTINCT outgoing) as Outgoing, COUNT(DISTINCT incoming) + COUNT(DISTINCT outgoing) as Total\nORDER BY Total desc\nLIMIT 10\n\n\n",
          "width": 6,
          "height": 2,
          "x": 6,
          "y": 4,
          "type": "bar",
          "selection": {
            "key": "n.City",
            "index": "n.City",
            "value": "Total"
          },
          "settings": {
            "colors": "set1",
            "legend": true,
            "showOptionalSelections": true,
            "styleRules": [
              {
                "field": "",
                "condition": "=",
                "value": "",
                "customization": "bar color",
                "customizationValue": "black"
              }
            ],
            "barValues": true,
            "groupMode": "stacked",
            "hideSelections": false
          }
        },
        {
          "title": "Problem7",
          "query": "MATCH PATH=(p:Airport)-[:BEGIN_ROUTE]->(o:Route)-[:END_ROUTE]->(p1:Airport)\nWHERE p.City = \"Orlando\" AND p1.City = \"Houston\"\nRETURN PATH, p.City, p.Name, p1.City, p1.Name\n",
          "width": 6,
          "height": 2,
          "x": 0,
          "y": 6,
          "type": "graph",
          "selection": {
            "Airport": "Name",
            "Route": "Airline"
          },
          "settings": {
            "nodePositions": {
              "39079": [
                -12.407167856053226,
                9.726911508137494
              ],
              "57346": [
                -13.731551730392974,
                -14.42932443727587
              ],
              "70954": [
                -13.725216007057801,
                -27.560654649547633
              ],
              "77912": [
                -20.25257030433427,
                20.20926279949424
              ]
            },
            "frozen": true
          }
        },
        {
          "title": "Problem8",
          "query": "MATCH PATH=(p:Airport)-[:BEGIN_ROUTE]->(o:Route)-[:END_ROUTE]->(p1:Airport)\nWHERE p.City = \"Seattle\" AND p1.City = \"New York\" AND o.Stops < 1\nRETURN PATH, p.City, p.Name, p1.City, p1.Name, o.Stops\n\n\n",
          "width": 5,
          "height": 2,
          "x": 6,
          "y": 6,
          "type": "graph",
          "selection": {
            "Airport": "Name",
            "Route": "Airline"
          },
          "settings": {
            "nodePositions": {
              "20606": [
                -5.048733713559997,
                -2.5773563329950266
              ],
              "25793": [
                4.162736414087387,
                17.314464444953963
              ],
              "28095": [
                8.136594413108197,
                4.909906061182142
              ],
              "35593": [
                5.183439651272424,
                -7.874502222050431
              ],
              "74202": [
                -5.354390705220575,
                10.415872436886431
              ]
            },
            "frozen": true
          }
        },
        {
          "title": "Problem9",
          "query": "MATCH PATH=(p:Airport)-[:BEGIN_ROUTE]->(o:Route)-[:END_ROUTE]->(p1:Airport)\nWHERE p.City = \"New York\" AND o.Stops = 0\nRETURN PATH, p.City, p.Name, p1.City, p1.Name, o.Stops\n\n",
          "width": 11,
          "height": 2,
          "x": 0,
          "y": 8,
          "type": "graph",
          "selection": {
            "Airport": "Name",
            "Route": "Airline"
          },
          "settings": {
            "nodePositions": {
              "15": [
                105.47655926017573,
                153.88350667569122
              ],
              "72": [
                380.76395028389663,
                -614.258323316688
              ],
              "99": [
                352.76685737149234,
                -638.9680072988315
              ],
              "144": [
                133.36004169206657,
                -218.60409538225505
              ],
              "154": [
                99.83712476926839,
                261.01200886038197
              ],
              "176": [
                -324.82429883760466,
                34.09447932552857
              ],
              "191": [
                224.41391946164075,
                -91.10628090115539
              ],
              "245": [
                -346.16570992772165,
                328.02734700121607
              ],
              "270": [
                128.66985130019677,
                217.4159965910552
              ],
              "299": [
                -272.3601681852165,
                303.5405432594213
              ],
              "336": [
                -72.05373438924725,
                267.2091185653592
              ],
              "341": [
                -394.0454751152311,
                297.92446696992647
              ],
              "342": [
                -307.7600293474173,
                -71.21909711508573
              ],
              "347": [
                84.75779169200163,
                331.171871019816
              ],
              "417": [
                39.7360907403795,
                385.89427362035815
              ],
              "473": [
                -386.1906080283564,
                134.1058372299921
              ],
              "498": [
                -366.6872213906215,
                265.09829815083543
              ],
              "502": [
                -126.83402018930146,
                171.897260392234
              ],
              "574": [
                148.30906204929934,
                212.66883562977688
              ],
              "592": [
                -47.7346446166988,
                391.1541557965723
              ],
              "596": [
                -404.54126858545953,
                204.3160756711377
              ],
              "601": [
                -156.95896043769613,
                433.9729007119244
              ],
              "627": [
                96.43408936604222,
                210.67582066921113
              ],
              "635": [
                -321.2360459558896,
                -54.58473386056601
              ],
              "668": [
                -214.91810809069543,
                419.56184176025045
              ],
              "725": [
                -388.91616176012815,
                95.21893550945792
              ],
              "795": [
                63.30232248745492,
                346.5043243823164
              ],
              "1049": [
                -386.1688424243266,
                184.7458393374869
              ],
              "1059": [
                23.5472736465838,
                396.16434884625744
              ],
              "1100": [
                -307.111187173889,
                356.39819198883066
              ],
              "1186": [
                -338.97466338979814,
                288.88424352264815
              ],
              "1196": [
                -138.40679167839053,
                256.3321720743914
              ],
              "1318": [
                5.296281162836521,
                437.21207978441623
              ],
              "1346": [
                -351.87943074316354,
                138.40270344550368
              ],
              "1350": [
                -214.09434311571601,
                396.75653155594983
              ],
              "1484": [
                -114.23220525587507,
                403.65097907023573
              ],
              "1510": [
                -332.61758930551935,
                -74.72258843467353
              ],
              "1514": [
                1.9959415430040464,
                363.18392234677395
              ],
              "1548": [
                -416.00567479663454,
                109.7152503490115
              ],
              "1571": [
                -167.84172127179127,
                -33.07894337793711
              ],
              "1621": [
                -379.63500785773783,
                -10.511478089869787
              ],
              "1633": [
                -357.0889868946437,
                75.71074174108267
              ],
              "1655": [
                37.06295244807222,
                354.08622193815273
              ],
              "1699": [
                -299.2086160309513,
                401.3657775498351
              ],
              "1704": [
                -382.8234781157351,
                47.80529257459542
              ],
              "1705": [
                87.71578166140863,
                171.83162803149006
              ],
              "1706": [
                -390.82686472856125,
                62.26587358523503
              ],
              "1707": [
                -239.46395256715508,
                441.4455139036035
              ],
              "1709": [
                -425.870832137334,
                205.77311966986903
              ],
              "1712": [
                -29.759868868399174,
                424.3577122954747
              ],
              "1716": [
                87.73120904572775,
                350.5475778780333
              ],
              "1723": [
                -365.61297543439804,
                218.6592165973197
              ],
              "1724": [
                143.4055913614117,
                259.1563024547633
              ],
              "1766": [
                -244.16707604335053,
                168.34442019563613
              ],
              "1794": [
                -246.19047743022742,
                390.8386115855493
              ],
              "1813": [
                128.43347091126685,
                249.30266948014216
              ],
              "1821": [
                -188.7952604515912,
                457.46250302661844
              ],
              "1825": [
                -296.04614631252963,
                -24.211586326780623
              ],
              "1831": [
                -199.12092252330703,
                430.538931269418
              ],
              "1836": [
                -403.85471881914617,
                73.89149824963631
              ],
              "1864": [
                -288.38880349394856,
                -104.10717724019749
              ],
              "1887": [
                -437.8332562434327,
                131.8911909496615
              ],
              "2002": [
                -273.6876221021784,
                386.2053913408469
              ],
              "2012": [
                -276.1299547619773,
                -66.8381949564139
              ],
              "2083": [
                -324.1691088666368,
                288.7436742440302
              ],
              "2089": [
                11.956861592592617,
                103.90420257638283
              ],
              "2092": [
                58.33134873972518,
                385.3717683270833
              ],
              "2100": [
                -256.96825610489395,
                -79.33711274039553
              ],
              "2115": [
                -321.7877132234371,
                338.23587623758084
              ],
              "2178": [
                -243.37240154673958,
                -40.12334393724247
              ],
              "2181": [
                -170.28562447577966,
                67.85851210906645
              ],
              "2432": [
                -121.77875083100881,
                -3.428863396177763
              ],
              "2436": [
                -157.79055872210657,
                400.33656829660487
              ],
              "2517": [
                -179.16906838221757,
                416.66376597102095
              ],
              "2540": [
                -353.363087335168,
                357.6674191836595
              ],
              "2574": [
                -368.00574961813203,
                35.17216538944049
              ],
              "2579": [
                115.67492030844461,
                173.12128291719068
              ],
              "2609": [
                -36.538964736304024,
                446.14762173003163
              ],
              "2651": [
                -318.2556948414111,
                -14.516695898338494
              ],
              "2708": [
                -75.85129510187713,
                434.9867409063035
              ],
              "2730": [
                -439.84785476359326,
                168.38416049668743
              ],
              "2731": [
                -79.82104348942974,
                27.5448451663707
              ],
              "2737": [
                -410.775464051594,
                225.6732150715443
              ],
              "2738": [
                -377.387907689787,
                12.137791071610746
              ],
              "2740": [
                -404.05218236490236,
                140.1590022017043
              ],
              "2744": [
                -298.3897385720454,
                375.4362242793826
              ],
              "2745": [
                22.98045547389416,
                228.72163214899268
              ],
              "2748": [
                119.27121919017175,
                265.222205162871
              ],
              "2749": [
                -54.37823220050478,
                -244.93589555826492
              ],
              "2753": [
                105.45360869156934,
                321.7361479562342
              ],
              "2755": [
                -15.504649996589924,
                404.7802540928745
              ],
              "2756": [
                -246.99581755028083,
                -101.72457938390556
              ],
              "2787": [
                86.09456410946221,
                151.94390481333173
              ],
              "2827": [
                -282.0866590008387,
                -82.8307123371633
              ],
              "2830": [
                -216.07094363064007,
                -62.002422676540355
              ],
              "2915": [
                -273.7696052906711,
                422.2325624483757
              ],
              "2931": [
                -367.0068481447115,
                301.77606912879264
              ],
              "3170": [
                -72.70636858360324,
                416.9715018616419
              ],
              "3207": [
                -414.7870251154466,
                267.6473969070332
              ],
              "3249": [
                131.15082781802747,
                -163.73145156693377
              ],
              "3254": [
                114.70608051927451,
                210.26499707846452
              ],
              "3255": [
                443.7983392791089,
                -582.7717437702973
              ],
              "3259": [
                526.0154256379906,
                -538.1274268412586
              ],
              "3260": [
                406.1947006776001,
                -584.7516618668426
              ],
              "3263": [
                -344.4743923107931,
                -30.036869006563318
              ],
              "3264": [
                522.599999025881,
                -499.96431548778133
              ],
              "3270": [
                -374.3945514561094,
                237.13445888974343
              ],
              "3274": [
                473.0334179575359,
                -606.67661340302
              ],
              "3285": [
                -118.2900003538082,
                433.6499409372824
              ],
              "3287": [
                86.39569532504744,
                -183.82030818149497
              ],
              "3289": [
                -80.32294690274368,
                -179.9837260357652
              ],
              "3316": [
                308.17497837702064,
                -627.7882123760106
              ],
              "3321": [
                163.53904107035066,
                -196.88311631617015
              ],
              "3333": [
                266.9117955554072,
                -182.41900374834862
              ],
              "3336": [
                -325.1660777416261,
                385.73045124380985
              ],
              "3350": [
                539.7786385207756,
                -561.2148032030442
              ],
              "3361": [
                531.1664044440749,
                -446.04840118549635
              ],
              "3366": [
                190.3361515233262,
                -182.15834242671207
              ],
              "3370": [
                221.3715887640438,
                -138.31125171899126
              ],
              "3376": [
                71.66735922148199,
                -273.08529416654847
              ],
              "3377": [
                -197.47388836888493,
                -51.0715469647738
              ],
              "3382": [
                95.8528311775169,
                183.1457812860721
              ],
              "3385": [
                -102.9957155753473,
                -193.45075252417718
              ],
              "3408": [
                389.4835251883,
                -231.68941340020052
              ],
              "3411": [
                108.04925445089758,
                -237.4533433333323
              ],
              "3413": [
                25.21322553562386,
                -200.3458904101938
              ],
              "3421": [
                5.820951239228258,
                402.1897224613877
              ],
              "3422": [
                -17.943995833905714,
                -222.51125065935454
              ],
              "3426": [
                170.1743386332555,
                -136.4443470497856
              ],
              "3427": [
                543.4460748636834,
                -520.5694244493462
              ],
              "3444": [
                -358.1196883587514,
                -9.301478777785087
              ],
              "3445": [
                367.1248904276089,
                -344.8195269808629
              ],
              "3446": [
                -21.15798412950427,
                -198.62999735894172
              ],
              "3460": [
                520.5877524534128,
                -575.0434554068909
              ],
              "3470": [
                274.4009088219909,
                -152.22933465717117
              ],
              "3473": [
                -334.1979904187321,
                1.6790635555283282
              ],
              "3476": [
                498.917242326163,
                -571.603455226881
              ],
              "3478": [
                384.6606723746424,
                -289.76759054264295
              ],
              "3482": [
                92.25827075793546,
                -254.52275126988621
              ],
              "3485": [
                545.8375125403346,
                -491.5099405853198
              ],
              "3490": [
                219.14079044226142,
                -195.70401351921402
              ],
              "3497": [
                343.6960571193279,
                -426.8480122938237
              ],
              "3511": [
                256.14206906959043,
                -119.15126960879381
              ],
              "3512": [
                -1.6599839347696588,
                -230.30960900097705
              ],
              "3514": [
                74.29708673821979,
                -98.90391211229478
              ],
              "3517": [
                438.61323330801144,
                -611.2019202851822
              ],
              "3520": [
                -286.98731381724497,
                -21.68650251534408
              ],
              "3522": [
                428.20413183359113,
                -269.120572575138
              ],
              "3528": [
                -306.87067516540674,
                -44.220938897133856
              ],
              "3529": [
                351.4804935910343,
                -609.5728623154833
              ],
              "3531": [
                -293.6098915336664,
                326.8662461149427
              ],
              "3545": [
                5.820245583630548,
                -202.12031416191587
              ],
              "3547": [
                564.5181838279317,
                -470.9065327584218
              ],
              "3548": [
                -407.4583831810913,
                176.49881040261454
              ],
              "3551": [
                148.61809535863347,
                -323.17532194951434
              ],
              "3552": [
                358.1155917673922,
                -163.78484749562088
              ],
              "3559": [
                54.36483934484111,
                -290.5914085474712
              ],
              "3593": [
                338.8049493422154,
                -182.9213124083397
              ],
              "3597": [
                -104.19944658104953,
                124.81531249309391
              ],
              "3606": [
                88.50145592841866,
                -149.7471059943006
              ],
              "3611": [
                512.9078037899379,
                -489.84450221169254
              ],
              "3617": [
                -389.8951128940288,
                26.119344575731922
              ],
              "3620": [
                116.64349887829775,
                -124.91787216349229
              ],
              "3630": [
                261.0495187819573,
                -92.70889743680623
              ],
              "3645": [
                398.4653579154165,
                -630.6555347477852
              ],
              "3649": [
                129.7288350697999,
                304.7441466613142
              ],
              "3658": [
                40.02750947182301,
                -181.95193433752823
              ],
              "3661": [
                92.33933814232041,
                -32.5012297815755
              ],
              "3662": [
                298.95949143253813,
                -82.39794005991692
              ],
              "3675": [
                496.86050727550867,
                -530.8127598030903
              ],
              "3676": [
                184.89858094994008,
                -110.29082377529754
              ],
              "3677": [
                -232.35804068463005,
                355.67856267587683
              ],
              "3678": [
                -35.48529891703871,
                -224.87239209949755
              ],
              "3725": [
                71.0306218044764,
                316.49122076965506
              ],
              "3746": [
                -406.9613135605599,
                100.3080972147587
              ],
              "3777": [
                -175.58850880825943,
                -47.42931522496448
              ],
              "3781": [
                90.1244324773137,
                287.7840902021117
              ],
              "3794": [
                329.97679879701184,
                -625.5341641706054
              ],
              "3797": [
                542.5996147086646,
                -470.1356038927925
              ],
              "3800": [
                405.3719606038545,
                -216.2808446681344
              ],
              "3801": [
                450.09258930330265,
                -626.5711600144951
              ],
              "3802": [
                489.1618138071176,
                -589.6282375169553
              ],
              "3803": [
                375.08958236986865,
                -630.5884110989339
              ],
              "3805": [
                80.36995956431824,
                131.363971353415
              ],
              "3819": [
                465.8561179705392,
                -574.4036076274601
              ],
              "3848": [
                158.99014487729468,
                -341.37706648593024
              ],
              "3849": [
                60.795590260724005,
                132.22330945170415
              ],
              "3889": [
                418.8109429493849,
                -624.4640462159127
              ],
              "4043": [
                63.69071991578377,
                367.1100653424453
              ],
              "4086": [
                572.5056545079287,
                -443.57960811055693
              ],
              "4497": [
                81.28499418529314,
                197.0588026251166
              ],
              "6827": [
                111.45201414760928,
                289.6110136429612
              ],
              "14923": [
                -132.18011128063523,
                20.642197832107826
              ],
              "14966": [
                -184.99097635704481,
                139.968144627816
              ],
              "17445": [
                7.041958058288864,
                60.182743128490785
              ],
              "17448": [
                224.92609827483568,
                -235.10388353687512
              ],
              "19450": [
                -231.77446272196386,
                211.56993581360862
              ],
              "19451": [
                -329.2820628940493,
                151.16407084451683
              ],
              "19452": [
                1.0163614749304588,
                282.89578506819026
              ],
              "19453": [
                -238.39975113308313,
                60.86931848514391
              ],
              "19454": [
                -265.8611502787616,
                233.27409419875377
              ],
              "19455": [
                -2.985452637850975,
                132.7750352437711
              ],
              "19456": [
                88.05004541321017,
                -63.57551238096262
              ],
              "19457": [
                31.791525050938937,
                -47.72228467665321
              ],
              "19458": [
                45.5997094592318,
                231.0513588697939
              ],
              "19459": [
                -77.08953392799502,
                350.06741466559816
              ],
              "19460": [
                -272.5692897018733,
                122.6900715082374
              ],
              "19461": [
                -16.623841134075057,
                -39.59133204555326
              ],
              "19462": [
                74.80193637357426,
                8.739375267132312
              ],
              "19463": [
                -45.56132565232261,
                -118.52161292116779
              ],
              "19464": [
                -209.39659996700087,
                329.16360166261984
              ],
              "19465": [
                -118.08929404255585,
                -60.914056456140315
              ],
              "19466": [
                61.24073873261495,
                -65.18707250915463
              ],
              "19467": [
                123.68153473257615,
                -16.26470837508417
              ],
              "19468": [
                19.38532530696485,
                211.9571556298689
              ],
              "19469": [
                -70.4406759730457,
                299.26758721090425
              ],
              "19470": [
                -276.9224148041699,
                225.28907723832083
              ],
              "19471": [
                -132.6057477100329,
                31.70657531502409
              ],
              "19472": [
                -35.6719979832705,
                274.5114376265224
              ],
              "19473": [
                -102.62473102445567,
                59.695642765520766
              ],
              "19474": [
                -141.48400852994996,
                300.0747007030935
              ],
              "19475": [
                -270.68720482080363,
                281.0849099323059
              ],
              "19476": [
                -2.5128407775945796,
                297.19494557079395
              ],
              "19477": [
                -214.13122589293994,
                308.5293190616406
              ],
              "19478": [
                -137.12262780840322,
                -78.42666449799297
              ],
              "19479": [
                -167.80575072393594,
                258.36902300049866
              ],
              "19480": [
                -117.01009788830746,
                347.56035318041035
              ],
              "19481": [
                -256.7341110097389,
                204.01830982080892
              ],
              "19482": [
                -99.98083250560866,
                167.1092911267919
              ],
              "19483": [
                -231.92892266789116,
                30.850455918576298
              ],
              "19484": [
                -125.15425269037402,
                212.86823666558718
              ],
              "19485": [
                -310.16072390687725,
                137.7487521290787
              ],
              "19486": [
                -88.37280667118631,
                -109.12111160462797
              ],
              "19487": [
                -30.69148135679111,
                -100.57230564268669
              ],
              "19488": [
                -115.47470778191492,
                318.0010616616496
              ],
              "19489": [
                -148.09937935585558,
                91.93214567201095
              ],
              "19490": [
                143.54145896611973,
                10.047311947335462
              ],
              "19491": [
                -6.398492537619373,
                -77.37038660173333
              ],
              "19492": [
                -168.0069187926511,
                300.9262198300885
              ],
              "19493": [
                -289.2791908741037,
                88.59951769762938
              ],
              "19494": [
                -263.96392221371184,
                19.697422412281085
              ],
              "19495": [
                97.4812591000364,
                -20.013491223162987
              ],
              "19496": [
                68.91561481403326,
                -26.749156870211316
              ],
              "19497": [
                -226.25039754542624,
                257.7510091572136
              ],
              "19498": [
                -142.1782066495703,
                272.7735937781927
              ],
              "19499": [
                -163.2512697803222,
                37.813285080936225
              ],
              "19500": [
                -281.4288703213994,
                192.9081969995994
              ],
              "19501": [
                -214.69232710035,
                31.563515070839617
              ],
              "19502": [
                -27.04537193618699,
                189.49033666287195
              ],
              "19503": [
                -292.49709377506974,
                39.29300087075663
              ],
              "19504": [
                43.209398055539125,
                260.3504921065982
              ],
              "19505": [
                -77.6429458923227,
                -47.793865068398176
              ],
              "19506": [
                -11.811609866954079,
                232.35164451198492
              ],
              "19507": [
                24.872400795800736,
                -72.7368173305533
              ],
              "19508": [
                -227.63282283621126,
                78.76998992675877
              ],
              "19509": [
                96.92595419388681,
                33.74454748387136
              ],
              "19510": [
                -264.1679604960656,
                87.02898837500842
              ],
              "19626": [
                318.81508385110965,
                -340.7624721452694
              ],
              "19627": [
                241.7331440234987,
                -298.99766778828234
              ],
              "19628": [
                412.1772717761861,
                -564.0672823697734
              ],
              "19629": [
                292.6783192194696,
                -273.95144427835265
              ],
              "19630": [
                191.57720553675605,
                -424.158612051909
              ],
              "19631": [
                481.2541078075662,
                -488.7641351665825
              ],
              "19632": [
                274.6095788730986,
                -339.5703477318502
              ],
              "19633": [
                359.8620837639805,
                -283.2803407309663
              ],
              "19634": [
                408.9449016374474,
                -411.3832416837052
              ],
              "19635": [
                328.87820020271835,
                -551.6822632606896
              ],
              "19636": [
                378.3589355097137,
                -564.885575175008
              ],
              "19637": [
                443.3404538690219,
                -508.15428981598325
              ],
              "19638": [
                197.35715966460532,
                -403.1903310783264
              ],
              "19639": [
                357.9322017616833,
                -252.71407752510206
              ],
              "19640": [
                228.81457497819224,
                -366.02393837043684
              ],
              "19641": [
                447.52392852682937,
                -375.6590766231391
              ],
              "19642": [
                411.77102674571285,
                -302.2025176756301
              ],
              "19643": [
                320.656602011823,
                -301.5335114409996
              ],
              "19644": [
                271.4070378187875,
                -286.2041991847433
              ],
              "19645": [
                416.57547264596724,
                -342.0131094483095
              ],
              "19646": [
                430.22229278747176,
                -529.3756633642141
              ],
              "19647": [
                434.7950347491237,
                -325.67764334537765
              ],
              "19648": [
                394.4717355045074,
                -386.6874029018212
              ],
              "19649": [
                429.9355965353836,
                -502.9885430288193
              ],
              "19650": [
                491.7592029909156,
                -436.3150305033711
              ],
              "19651": [
                248.2271678141027,
                -358.0882200221973
              ],
              "19652": [
                314.5390126657718,
                -252.0345225175673
              ],
              "21220": [
                -302.679557695397,
                240.66300036023088
              ],
              "21221": [
                9.075409564257155,
                237.90333022558568
              ],
              "21801": [
                97.1158855853357,
                21.842849605242094
              ],
              "21816": [
                342.2343123720645,
                -535.7541981746654
              ],
              "21817": [
                259.4933396863565,
                -358.8052525296343
              ],
              "21818": [
                308.18670261099965,
                -235.45231143814743
              ],
              "23451": [
                11.244107172089436,
                -121.20033986499999
              ],
              "23452": [
                -263.22412210974005,
                247.72466227377532
              ],
              "23453": [
                -209.1733658593152,
                230.52372114005036
              ],
              "23454": [
                -272.2838663286582,
                139.74542468310656
              ],
              "23455": [
                -66.67189551558663,
                284.93176763410264
              ],
              "23456": [
                -94.82140966266827,
                214.1536558760511
              ],
              "23457": [
                -75.58523178785458,
                155.58467012231807
              ],
              "23458": [
                -134.1320374121887,
                192.70394642568436
              ],
              "23459": [
                -4.646924024444928,
                44.013996580817015
              ],
              "23460": [
                -28.009852852938337,
                334.69014501646967
              ],
              "23461": [
                -315.92346210131075,
                91.0601392684864
              ],
              "23503": [
                219.57903340731224,
                -380.31745451780176
              ],
              "24412": [
                -299.7052362983026,
                255.4635650328546
              ],
              "24413": [
                -141.897274174649,
                148.16675435558702
              ],
              "24872": [
                4.499701887598126,
                -115.07966083778248
              ],
              "24873": [
                -206.820402516953,
                297.6911336751746
              ],
              "24874": [
                -184.4094613623473,
                162.28942600488526
              ],
              "24889": [
                228.39119857259575,
                -389.2974371035888
              ],
              "25331": [
                -140.40126537376042,
                42.14125921395851
              ],
              "25530": [
                -104.28787458774417,
                365.440953258137
              ],
              "25531": [
                -241.54159633538274,
                274.3022552495411
              ],
              "25532": [
                -159.9717790423639,
                22.809990522700893
              ],
              "25533": [
                -286.75717635763147,
                203.299324123215
              ],
              "26043": [
                -302.60780225590463,
                165.37113797604272
              ],
              "26286": [
                -259.463545082223,
                71.99069540421641
              ],
              "26287": [
                -58.00899188245308,
                343.85160707177795
              ],
              "26288": [
                -170.27333310672537,
                328.1347403004811
              ],
              "26289": [
                36.9827851439784,
                285.7901411501859
              ],
              "26599": [
                -274.4473126756434,
                242.51809115184042
              ],
              "26600": [
                -255.9918587782344,
                133.50021120866901
              ],
              "26601": [
                -52.836039859366466,
                325.0283046636167
              ],
              "26602": [
                -36.574747486894516,
                264.03517441108426
              ],
              "26603": [
                0.5114978279986422,
                307.4975924625089
              ],
              "26604": [
                -297.688113822963,
                227.75623931169952
              ],
              "26605": [
                -149.0502307571223,
                134.57457950292923
              ],
              "26606": [
                -112.2409741010745,
                203.64315221379152
              ],
              "26607": [
                -282.7229395213101,
                132.4379982896421
              ],
              "26608": [
                -96.29683949377059,
                338.898240826511
              ],
              "26609": [
                -33.39364481580601,
                197.85257396880604
              ],
              "26610": [
                30.773035675422697,
                -86.88047171028684
              ],
              "26611": [
                110.74119886853315,
                20.282499598174994
              ],
              "27278": [
                9.390950345440867,
                -133.4987317727256
              ],
              "27279": [
                -253.0477029836393,
                122.24572385644414
              ],
              "27280": [
                -40.7952158820206,
                282.3719068821689
              ],
              "27281": [
                -194.05934329853542,
                143.99949186649965
              ],
              "27282": [
                36.05446750776927,
                41.0952828523283
              ],
              "27283": [
                -111.91845711058207,
                329.0258661099344
              ],
              "27284": [
                -232.57165795315638,
                5.800636517023179
              ],
              "27285": [
                50.75576885076362,
                -89.72788805298781
              ],
              "27286": [
                107.18990457124139,
                8.329897793049213
              ],
              "27906": [
                10.871159307195025,
                123.22107845507138
              ],
              "27907": [
                -114.89586996601328,
                -97.8002618050755
              ],
              "27908": [
                -249.4836124403552,
                48.4660442364764
              ],
              "27909": [
                3.836778383185754,
                170.049280073076
              ],
              "27910": [
                -22.545946863567096,
                129.2108388193382
              ],
              "27911": [
                -78.24225037692823,
                73.31124140191734
              ],
              "27912": [
                35.87708363066494,
                -35.6547937898255
              ],
              "27913": [
                -321.3717666057738,
                132.70775536287533
              ],
              "27914": [
                78.95940077007303,
                47.30374584022442
              ],
              "27915": [
                -0.7476674903604201,
                7.643927063022611
              ],
              "27916": [
                -285.3419994282848,
                25.002123942677617
              ],
              "27917": [
                -22.635512776317935,
                -8.4489858273848
              ],
              "27918": [
                75.86272581336554,
                -6.975592058724348
              ],
              "27919": [
                39.08605316475335,
                148.95840267287642
              ],
              "27920": [
                -192.90077323820563,
                299.40180976108417
              ],
              "27921": [
                30.755827136867328,
                -136.09788955199468
              ],
              "27922": [
                -188.87207774366487,
                2.4759367321860632
              ],
              "27923": [
                110.44883185304273,
                -35.0687227515333
              ],
              "27924": [
                -205.08264507850586,
                -16.231992796562814
              ],
              "27925": [
                33.13941504495795,
                -5.236494078397778
              ],
              "27926": [
                -27.75246626122675,
                9.791198738281755
              ],
              "27927": [
                -62.03082959187701,
                -78.515326901168
              ],
              "27928": [
                13.683979874871495,
                275.42263213522097
              ],
              "27929": [
                -240.59246103460768,
                181.01365022893413
              ],
              "27930": [
                -176.3899869554158,
                268.92649587463353
              ],
              "27931": [
                -122.5135695390563,
                367.0394338018919
              ],
              "27932": [
                18.633033172042524,
                157.45500144627943
              ],
              "27933": [
                -160.4935562183414,
                348.4550466040261
              ],
              "27934": [
                -301.73457659819064,
                67.73527889219021
              ],
              "27935": [
                57.144858972082744,
                203.58355741053217
              ],
              "27936": [
                -97.88338673321265,
                -82.76549946271487
              ],
              "27937": [
                4.5918147128134,
                49.762718072292074
              ],
              "27938": [
                -107.0818473393664,
                287.2010725021003
              ],
              "27939": [
                -308.5693883037639,
                126.75721689771433
              ],
              "27940": [
                40.52279053780066,
                177.47293147710354
              ],
              "27941": [
                143.41006936260646,
                22.061396879244565
              ],
              "27942": [
                -324.39765678385777,
                84.13443224182853
              ],
              "27943": [
                188.89427750878292,
                -66.5941505641277
              ],
              "27944": [
                -192.69681736652342,
                66.54441946684709
              ],
              "27945": [
                -246.89280920183637,
                23.34684701349622
              ],
              "27946": [
                -223.36296206817957,
                290.86493503273886
              ],
              "27947": [
                -310.04909159854185,
                76.52345416848496
              ],
              "27948": [
                -186.02751127497066,
                -17.082745748226525
              ],
              "27949": [
                -248.65324753226494,
                311.29347685750014
              ],
              "27950": [
                -12.064773622423038,
                146.6255231519843
              ],
              "27951": [
                108.49284909155686,
                66.37539150435454
              ],
              "27952": [
                48.89889593676294,
                -7.0249516981307565
              ],
              "27953": [
                -75.14462668951472,
                -75.63648184683994
              ],
              "27954": [
                146.6689780030228,
                -9.477605042848447
              ],
              "27955": [
                -236.30310508948776,
                252.65942055326718
              ],
              "27956": [
                -53.48342566094151,
                -35.552506411263096
              ],
              "27957": [
                -195.6702783460794,
                339.1739679003299
              ],
              "27958": [
                -153.08086778479537,
                30.86970277529904
              ],
              "27959": [
                -296.04104590675104,
                196.003478339116
              ],
              "27960": [
                -326.0520377230854,
                163.54346862213004
              ],
              "27961": [
                -31.62219758127943,
                174.6953691802187
              ],
              "27962": [
                -238.6444793410556,
                286.89216293104244
              ],
              "27963": [
                -310.2030539781718,
                51.87371298080565
              ],
              "27964": [
                28.133951848293997,
                -121.02878013236909
              ],
              "27965": [
                -315.9039252658413,
                176.4815457678039
              ],
              "27966": [
                30.800266079993513,
                249.60988922759128
              ],
              "27967": [
                -59.95988481781707,
                -49.60850642783552
              ],
              "27968": [
                -88.01564484090008,
                -66.33206534920139
              ],
              "27969": [
                52.49090516427716,
                217.7684126136486
              ],
              "27980": [
                341.7705455919629,
                -314.4089598419446
              ],
              "27981": [
                137.44015371445587,
                -367.9874046028882
              ],
              "27982": [
                435.76500749962463,
                -377.90077817511707
              ],
              "27983": [
                395.51403528432076,
                -322.2532660584656
              ],
              "27984": [
                276.26288598184124,
                -453.7132644959157
              ],
              "27985": [
                146.76250317350699,
                -341.9635281601617
              ],
              "28421": [
                -253.52100715171474,
                229.2714081982694
              ],
              "28422": [
                -240.8392790461273,
                134.82681691946044
              ],
              "28423": [
                -62.851069277575604,
                332.36331531794747
              ],
              "28424": [
                -26.178374094128753,
                282.2655463113235
              ],
              "28425": [
                8.139353569424552,
                314.81965685674805
              ],
              "28426": [
                -287.35288173767555,
                221.13583731386333
              ],
              "28427": [
                -96.81480560930598,
                158.06071689594467
              ],
              "28428": [
                -134.11706135595216,
                203.83871579431036
              ],
              "28429": [
                -287.8938842425998,
                123.92314592234668
              ],
              "28430": [
                -100.94360831840362,
                310.69380513405656
              ],
              "28431": [
                -175.7793891885253,
                298.0006864518148
              ],
              "29491": [
                -188.17498554950984,
                29.734268794302665
              ],
              "29799": [
                20.376840793479747,
                298.174251178212
              ],
              "29800": [
                -301.9993195533773,
                182.75186812346763
              ],
              "29801": [
                -253.96326761736543,
                178.96345863834026
              ],
              "29802": [
                66.82462301011773,
                212.46136064608038
              ],
              "29803": [
                -175.3092493575398,
                -7.208519227231751
              ],
              "29804": [
                -36.821935384970914,
                324.3487095656196
              ],
              "30325": [
                -85.63721335877182,
                304.633543452432
              ],
              "31293": [
                29.97120913514159,
                228.79447539946662
              ],
              "31482": [
                32.012389279435276,
                191.8300836471644
              ],
              "31822": [
                -219.60069200877513,
                323.03902078181454
              ],
              "31823": [
                33.514259709237905,
                210.2808636111094
              ],
              "34776": [
                -282.3507510051702,
                274.7067724958269
              ],
              "34777": [
                49.55856824064195,
                165.6481674723672
              ],
              "34778": [
                8.541937359067827,
                -105.81693419369591
              ],
              "34779": [
                -116.14706987509928,
                -83.21820200946784
              ],
              "34780": [
                -240.79081542605235,
                43.56631470093378
              ],
              "34781": [
                -273.85873636278257,
                255.03043612653545
              ],
              "34782": [
                -8.450801541843173,
                123.05862348760417
              ],
              "34783": [
                99.73105904165942,
                -64.3284928447745
              ],
              "34784": [
                -284.34557893652766,
                66.46174152012304
              ],
              "34785": [
                21.660309610540377,
                -37.79192572023821
              ],
              "34786": [
                -191.43429544467338,
                218.74033093332451
              ],
              "34787": [
                10.271171457939783,
                0.49788517122873277
              ],
              "34788": [
                56.46859193921583,
                236.8435393175299
              ],
              "34789": [
                -282.8505624428829,
                145.25076039473683
              ],
              "34790": [
                -10.670918423115857,
                -15.836966613514386
              ],
              "34791": [
                -5.937287900160826,
                -43.33599528740826
              ],
              "34792": [
                64.03812746406172,
                21.42616603538065
              ],
              "34793": [
                -34.23993326375416,
                -138.14954900187027
              ],
              "34794": [
                -199.7633335887205,
                309.58053474704496
              ],
              "34795": [
                -113.36477769306634,
                -49.160583637407015
              ],
              "34796": [
                48.283432234678976,
                -47.78669663525718
              ],
              "34797": [
                37.703083271922054,
                -143.87895464768624
              ],
              "34798": [
                130.634715969926,
                -23.967341699071362
              ],
              "34799": [
                -7.973499238449065,
                320.83404760872764
              ],
              "34800": [
                148.52287104081893,
                -110.95300391157207
              ],
              "34801": [
                -59.79184954021087,
                292.42457917865136
              ],
              "34802": [
                -47.90651383788974,
                261.634987134662
              ],
              "34803": [
                119.48825469696496,
                -44.43622714783867
              ],
              "34804": [
                -67.16575215142966,
                215.98479222108375
              ],
              "34805": [
                -279.65565144881367,
                176.2247762212277
              ],
              "34806": [
                -143.21138578974637,
                313.08257504061925
              ],
              "34807": [
                -44.80248024415254,
                345.04133149220803
              ],
              "34808": [
                -25.658325080558537,
                22.55366511748013
              ],
              "34809": [
                21.817455128931346,
                258.8776409367301
              ],
              "34810": [
                -133.98041544353208,
                -54.28742218355629
              ],
              "34811": [
                -68.8867016893862,
                -59.51351110889631
              ],
              "34812": [
                -183.39208567358259,
                282.7161180839873
              ],
              "34813": [
                -124.13444984627623,
                330.1768402290076
              ],
              "34814": [
                -86.69268022198051,
                153.5614175330313
              ],
              "34815": [
                -156.77671239748494,
                330.0033000271115
              ],
              "34816": [
                -148.1076788051891,
                196.46756450898715
              ],
              "34817": [
                46.91361603780947,
                198.5743356136033
              ],
              "34818": [
                -96.41802909395142,
                -95.25571752636964
              ],
              "34819": [
                -192.93441398163807,
                155.517116291288
              ],
              "34820": [
                -25.624648175491277,
                -111.17673559521042
              ],
              "34821": [
                -46.94726693757651,
                -20.092019602905193
              ],
              "34822": [
                12.859312966792954,
                41.077612341499126
              ],
              "34823": [
                -125.79818941515205,
                338.17792001122524
              ],
              "34824": [
                -327.8226716589967,
                123.44046503294132
              ],
              "34825": [
                -34.227997334281774,
                311.38732746169177
              ],
              "34826": [
                -158.58544439599484,
                106.05010599091132
              ],
              "34827": [
                125.31077709798612,
                38.83800661957045
              ],
              "34828": [
                5.073984463735869,
                -80.06118517119093
              ],
              "34829": [
                -302.4461056623523,
                88.0115342290124
              ],
              "34830": [
                -193.12812076572322,
                53.32101548009921
              ],
              "34831": [
                160.25205874280397,
                9.686358309561696
              ],
              "34832": [
                -276.3070483571679,
                10.831175225590826
              ],
              "34833": [
                93.27514528156685,
                -9.533398947887234
              ],
              "34834": [
                -233.8381694227885,
                304.9414721281874
              ],
              "34835": [
                -13.309800663476697,
                155.59775264241247
              ],
              "34836": [
                -297.41305423487927,
                211.75257554983264
              ],
              "34837": [
                57.89822259963568,
                -23.62768116289102
              ],
              "34838": [
                166.86243099032052,
                -45.70713673625052
              ],
              "34839": [
                -88.3166437649585,
                -52.48149283258767
              ],
              "34840": [
                -213.78500082419725,
                254.47687914163856
              ],
              "34841": [
                -20.679434516767266,
                324.186329813547
              ],
              "34842": [
                -46.78397695174922,
                -54.895462938404435
              ],
              "34843": [
                180.1781623092186,
                -30.549859968035168
              ],
              "34844": [
                -185.4817288953708,
                322.39807966270416
              ],
              "34845": [
                -159.17760809450644,
                9.368682899797932
              ],
              "34846": [
                -310.1023062604728,
                210.7668252120351
              ],
              "34847": [
                -211.08849219906924,
                52.88474808408483
              ],
              "34848": [
                -19.15856283128605,
                184.47000421361918
              ],
              "34849": [
                -250.1763939885243,
                296.89190779952406
              ],
              "34850": [
                -290.8379107538052,
                168.37855603067598
              ],
              "34851": [
                159.79074587693356,
                -83.7291845078645
              ],
              "34852": [
                -270.2878177502911,
                64.34536255245074
              ],
              "34853": [
                -200.5690700888452,
                11.821906487012283
              ],
              "34854": [
                49.37438251916934,
                268.27978663827537
              ],
              "34855": [
                -67.95904998170042,
                -33.41220166609293
              ],
              "34856": [
                -292.89200058892425,
                107.25537224680902
              ],
              "34857": [
                -78.582590947321,
                -85.31933255396734
              ],
              "34858": [
                -240.35901069109147,
                -11.516320528604266
              ],
              "34859": [
                46.95545549422744,
                -100.41820889869688
              ],
              "34860": [
                -213.03101159979914,
                93.06887422208635
              ],
              "34861": [
                119.21658480472962,
                11.762324645381465
              ],
              "34960": [
                196.3744546765231,
                -374.72822223502305
              ],
              "34961": [
                149.76257975662548,
                -404.2335664068702
              ],
              "34962": [
                459.2540530237793,
                -468.3996257470114
              ],
              "34963": [
                446.4652076666569,
                -467.4430728785638
              ],
              "34964": [
                303.5699179844044,
                -324.4591214313982
              ],
              "34965": [
                258.48538901859456,
                -315.4054491941495
              ],
              "34966": [
                347.5571308044587,
                -321.5339133326192
              ],
              "34967": [
                259.66710653180786,
                -301.76854689571195
              ],
              "34968": [
                464.28247603252373,
                -437.526072675424
              ],
              "34969": [
                406.56132936516417,
                -547.8611662520901
              ],
              "34970": [
                240.199413086043,
                -320.4619408903283
              ],
              "34971": [
                213.41747722280996,
                -323.57102009923403
              ],
              "34972": [
                280.20175069463176,
                -272.6081347340667
              ],
              "34973": [
                202.10156452509588,
                -427.3551028412437
              ],
              "34974": [
                127.59857739543739,
                -347.15700535756224
              ],
              "34975": [
                471.54173931554254,
                -481.777672242512
              ],
              "34976": [
                281.1117575638828,
                -348.47333752456643
              ],
              "34977": [
                257.66382429071564,
                -437.77398921635717
              ],
              "34978": [
                361.349993877908,
                -294.86137508656094
              ],
              "34979": [
                347.36305124748736,
                -545.5983864793212
              ],
              "34980": [
                393.37878167982427,
                -431.12346966632117
              ],
              "34981": [
                438.1320445157629,
                -488.1368275424508
              ],
              "34982": [
                347.7084122871544,
                -335.0932801604044
              ],
              "34983": [
                483.69041070870986,
                -468.76610326246833
              ],
              "34984": [
                329.6115521035991,
                -564.6363591792023
              ],
              "34985": [
                420.42972590482725,
                -521.354342831061
              ],
              "34986": [
                468.7874794545031,
                -517.2423929936825
              ],
              "34987": [
                370.1586791597997,
                -543.2022718288252
              ],
              "34988": [
                115.40708916650154,
                -361.67161736666145
              ],
              "34989": [
                173.51836597342086,
                -395.55149838568747
              ],
              "34990": [
                360.8321734399384,
                -566.7775775023463
              ],
              "34991": [
                471.3924203502,
                -502.64805965697894
              ],
              "34992": [
                144.56515431740192,
                -376.4755886516285
              ],
              "34993": [
                434.6747999785962,
                -552.3681685032032
              ],
              "34994": [
                479.6796684409655,
                -456.0759407486345
              ],
              "34995": [
                217.56806022621467,
                -411.2168015811485
              ],
              "34996": [
                397.5666839287292,
                -534.5343583558506
              ],
              "34997": [
                383.47949249360994,
                -514.8770134106259
              ],
              "34998": [
                199.95994366422835,
                -339.34335447589365
              ],
              "34999": [
                223.34462357412403,
                -224.6286455037678
              ],
              "35000": [
                312.70297259730245,
                -550.481776729879
              ],
              "35001": [
                406.889827591138,
                -522.2020980158395
              ],
              "35002": [
                344.8443465398756,
                -250.79356379290965
              ],
              "35003": [
                246.63708254077972,
                -382.1822900581848
              ],
              "35004": [
                452.87209795165427,
                -365.4111401897256
              ],
              "35005": [
                314.46655851119414,
                -283.291656401209
              ],
              "35006": [
                391.59403598916896,
                -283.33515431217415
              ],
              "35007": [
                287.73558191349247,
                -294.6953111851409
              ],
              "35008": [
                422.8811226716672,
                -351.05550844315314
              ],
              "35009": [
                166.58185120796887,
                -382.2168685668795
              ],
              "35010": [
                394.11160141779175,
                -334.9825772692102
              ],
              "35011": [
                191.1086354368622,
                -353.72042789626437
              ],
              "35012": [
                434.04395947927844,
                -341.1690455462873
              ],
              "35013": [
                264.94602480020274,
                -451.6917193574684
              ],
              "35014": [
                404.4501697510544,
                -393.0074028717891
              ],
              "35015": [
                180.25659790668328,
                -367.02254640669486
              ],
              "35016": [
                154.27820238913262,
                -351.8289846789133
              ],
              "35017": [
                440.14622212099397,
                -520.9413142641733
              ],
              "35018": [
                358.9859966107134,
                -532.0361253034466
              ],
              "35019": [
                236.75531858610734,
                -336.2202887919923
              ],
              "35020": [
                319.34569247047824,
                -238.56116085876405
              ],
              "36338": [
                -305.99711934426006,
                102.73756738005675
              ],
              "36339": [
                19.585331000244043,
                175.7818665658885
              ],
              "36340": [
                -146.1288320863879,
                350.189291156553
              ],
              "36341": [
                -254.4529975351562,
                -8.049627869048965
              ],
              "36839": [
                -58.05112559816299,
                311.22312605341835
              ],
              "36840": [
                -327.5776769172878,
                181.78788360463
              ],
              "37124": [
                -184.18750871159327,
                17.414186591973653
              ],
              "37125": [
                -101.19509827228816,
                324.5511035640839
              ],
              "37681": [
                -83.08596515595399,
                214.4208025735166
              ],
              "38052": [
                -15.435659851061796,
                265.52888410098797
              ],
              "38053": [
                -266.78056961447936,
                148.75391088972611
              ],
              "38054": [
                -187.00945825493616,
                263.2450241761762
              ],
              "38055": [
                34.94021830174312,
                52.96033886557806
              ],
              "38306": [
                244.40125175152735,
                -436.9852837122569
              ],
              "38599": [
                30.182848013299118,
                136.46389388086712
              ],
              "39037": [
                205.91119252010944,
                -364.8796236391188
              ],
              "39038": [
                387.9822101402467,
                -547.4411532280194
              ],
              "39039": [
                464.7284855253241,
                -451.60348461064626
              ],
              "42596": [
                -144.25451827730296,
                325.13531812898475
              ],
              "44513": [
                -242.9653574485276,
                4.506226493049155
              ],
              "44514": [
                -192.75178681702585,
                287.7517110626593
              ],
              "45873": [
                -325.10009106359195,
                106.3208772974407
              ],
              "46394": [
                -285.5855694373204,
                257.6794648160357
              ],
              "46395": [
                -242.18657214490403,
                144.96110943215146
              ],
              "46396": [
                -28.69738063574628,
                293.19157813805253
              ],
              "46397": [
                -10.453207244671225,
                287.60329018455695
              ],
              "46398": [
                -271.1906966233488,
                210.89247331361793
              ],
              "46399": [
                -135.54261919805174,
                137.2130593302405
              ],
              "46400": [
                -120.27592186147858,
                221.1367813616055
              ],
              "46401": [
                -298.41240872171153,
                122.10503617543807
              ],
              "46402": [
                -112.41839513482898,
                295.37298458070995
              ],
              "46403": [
                -161.70497313128547,
                279.6752503300032
              ],
              "48203": [
                -97.39356887900468,
                50.53698314221092
              ],
              "48204": [
                -134.22063311759393,
                292.7500566082517
              ],
              "48205": [
                -228.47970637307643,
                51.451948163957994
              ],
              "48504": [
                25.54038671117119,
                37.95243731241547
              ],
              "48505": [
                -143.35977474916325,
                101.27960324746773
              ],
              "49868": [
                -3.9759994279526247,
                226.15112914600806
              ],
              "50556": [
                34.129178903316706,
                165.88392867554515
              ],
              "50557": [
                -1.7767204254258515,
                -130.49683018881447
              ],
              "50558": [
                -285.60864709323175,
                245.55613044277305
              ],
              "50559": [
                -185.83168812969706,
                227.3801872789466
              ],
              "50560": [
                -69.66895590510325,
                311.2562466987137
              ],
              "50561": [
                -68.24187641752152,
                206.72623487908933
              ],
              "50562": [
                -153.34225883228711,
                159.04418457089102
              ],
              "50563": [
                -146.06281935989875,
                207.9496198993435
              ],
              "50564": [
                19.40813079413671,
                52.007176265229184
              ],
              "50607": [
                203.31920261263033,
                -383.8565745056908
              ],
              "51251": [
                -42.13161757846715,
                108.79712566214792
              ],
              "51252": [
                -94.98197332816001,
                178.090564350566
              ],
              "51312": [
                -213.50200120359605,
                -26.996598660147153
              ],
              "51533": [
                -219.86776109633956,
                46.083644573785435
              ],
              "51534": [
                -152.1509666830879,
                294.6862768513438
              ],
              "52310": [
                -200.5197964272097,
                213.13703043879963
              ],
              "52311": [
                -74.6540514810194,
                224.9297015736123
              ],
              "52312": [
                6.849868719192096,
                32.163817557961295
              ],
              "52313": [
                -221.63540790172766,
                2.116302314466812
              ],
              "52948": [
                -184.15990924095425,
                343.16623810522464
              ],
              "53512": [
                -260.2914683353172,
                49.95244416450452
              ],
              "53513": [
                -249.3154088740523,
                94.08683340006323
              ],
              "53701": [
                -277.41661474111686,
                107.43868221280619
              ],
              "54447": [
                -86.00833195274977,
                142.95095327165689
              ],
              "55142": [
                -221.39978033823888,
                270.2297464409277
              ],
              "55539": [
                -316.5498007062134,
                222.0647087048306
              ],
              "56850": [
                -132.08102965199402,
                87.31722033020328
              ],
              "57335": [
                360.71052668793266,
                -305.0557025990509
              ],
              "57336": [
                410.39194932533417,
                -421.87183139476264
              ],
              "57337": [
                356.47866726169974,
                -322.1445940068859
              ],
              "57338": [
                315.7127338879939,
                -536.1463908375149
              ],
              "57339": [
                347.20326917525705,
                -261.61294917847266
              ],
              "58244": [
                -266.06958049987605,
                177.92119914682462
              ],
              "58464": [
                -140.38154674557816,
                57.71452809536494
              ],
              "58948": [
                12.045851875278458,
                250.1228509397979
              ],
              "59673": [
                -259.4231230197759,
                279.60115029052713
              ],
              "60144": [
                13.736164172101772,
                140.26778977256217
              ],
              "60804": [
                -112.80816325629392,
                359.1313380861058
              ],
              "61344": [
                -251.90375841702888,
                219.42283425865293
              ],
              "61345": [
                -236.6053892964559,
                126.4237615788175
              ],
              "61346": [
                5.423971419243713,
                207.08328560426264
              ],
              "61347": [
                -193.21654368148558,
                271.01335268824187
              ],
              "61348": [
                25.509449628274723,
                61.554572459731965
              ],
              "61349": [
                -120.26001610840622,
                305.9333000053906
              ],
              "61350": [
                132.94324066910252,
                23.784504330719702
              ],
              "61351": [
                -237.1709798973792,
                264.6945287464924
              ],
              "61859": [
                -236.54191922671825,
                223.37763337156488
              ],
              "62689": [
                4.592499026271647,
                266.181778704254
              ],
              "63201": [
                -253.16399546071946,
                144.55404481658715
              ],
              "64192": [
                -207.51635810106416,
                220.57692067832352
              ],
              "64338": [
                -80.53024589709291,
                202.7851295205798
              ],
              "64714": [
                -6.559122693701729,
                -112.21214567247367
              ],
              "64715": [
                -204.9143441622145,
                -3.529024605193042
              ],
              "65312": [
                -230.60437779238308,
                317.10884576863737
              ],
              "65313": [
                -221.3082039800064,
                -14.020560997419683
              ],
              "65532": [
                -38.67430839165908,
                -34.72295015984603
              ],
              "66525": [
                -34.657060421483855,
                237.11527696237695
              ],
              "70758": [
                -277.8163704173217,
                61.49649230445073
              ],
              "70759": [
                -200.7402885251564,
                239.31927097042225
              ],
              "70760": [
                -220.2121212758475,
                246.226446979967
              ],
              "70761": [
                -65.11077479036055,
                321.6907496166385
              ],
              "70762": [
                -86.68592298956709,
                227.0870002983689
              ],
              "70763": [
                -272.45845462234956,
                35.6305959240256
              ],
              "70764": [
                -14.787721955300915,
                10.119861404838888
              ],
              "70765": [
                -0.5407613237355876,
                241.03907993608385
              ],
              "70766": [
                -5.443333907732091,
                256.36909029072143
              ],
              "70767": [
                -127.41114563477767,
                353.4426245904982
              ],
              "70768": [
                -215.4080515113967,
                14.58007645756278
              ],
              "70769": [
                -118.05671682009294,
                84.8942261726459
              ],
              "70770": [
                -90.09190911822358,
                287.22874827196284
              ],
              "70771": [
                16.176515573192713,
                190.63248690946867
              ],
              "70772": [
                -171.5619532251525,
                342.1160490208068
              ],
              "70773": [
                -269.91175182495186,
                193.89499374074936
              ],
              "70774": [
                -123.7406264843932,
                43.45191938239218
              ],
              "70775": [
                -239.2298164381127,
                99.75670725187615
              ],
              "70892": [
                222.91846881924323,
                -328.6399994920604
              ],
              "70893": [
                262.1287670458439,
                -424.69797488071936
              ],
              "70894": [
                222.7427733768865,
                -286.0710103529031
              ],
              "70895": [
                457.12681519975587,
                -501.6830127161548
              ],
              "70896": [
                354.1008869030911,
                -240.961783732064
              ],
              "70897": [
                344.80952304099196,
                -559.6526879103455
              ],
              "70898": [
                250.4630454357327,
                -348.2020291613239
              ],
              "70899": [
                315.8005629945749,
                -261.4314495220615
              ],
              "72101": [
                -170.8210051011138,
                6.912105359185238
              ],
              "73271": [
                -223.19775379824412,
                202.79714374637686
              ],
              "73272": [
                -311.9705412632295,
                153.43921897123104
              ],
              "73273": [
                -257.06298466901967,
                32.324863213834405
              ],
              "73274": [
                -254.58095361517326,
                239.73718405702903
              ],
              "73275": [
                -17.759527792499625,
                116.8738048833582
              ],
              "73276": [
                86.54894154954762,
                -51.90003276318728
              ],
              "73277": [
                -293.7066524721604,
                57.428995790564024
              ],
              "73278": [
                21.52590925925772,
                -25.90291533290837
              ],
              "73279": [
                60.824750477751955,
                246.8593403338069
              ],
              "73280": [
                -265.2618715473651,
                130.87669822406772
              ],
              "73281": [
                -6.009873408965026,
                -54.6780770445829
              ],
              "73282": [
                63.099169637452675,
                9.601012968665202
              ],
              "73283": [
                -41.90686742441734,
                -129.2808451370337
              ],
              "73284": [
                -202.44768933072905,
                320.1818701296638
              ],
              "73285": [
                -113.04784303081925,
                -37.69395098892616
              ],
              "73286": [
                52.555100223432355,
                -57.976155226890754
              ],
              "73287": [
                139.82230971963668,
                -28.497585760096378
              ],
              "73288": [
                -76.21128871386237,
                282.3770800095118
              ],
              "73289": [
                -21.049573729592232,
                300.73840552166484
              ],
              "73290": [
                -97.42194105898646,
                230.46890288869506
              ],
              "73291": [
                -113.58777793925584,
                62.158820839717144
              ],
              "73292": [
                -131.83688753503043,
                280.9170189323207
              ],
              "73293": [
                -138.0047801265262,
                -67.15330839278795
              ],
              "73294": [
                -27.25928278622264,
                247.44223670863545
              ],
              "73295": [
                22.2855696020126,
                281.7683213864257
              ],
              "73296": [
                -200.2507942365825,
                279.8487890946098
              ],
              "73297": [
                -98.43289821769382,
                354.8929214494981
              ],
              "73298": [
                -154.2627809419671,
                145.55192844512777
              ],
              "73299": [
                -122.65335584272398,
                200.6233331911977
              ],
              "73300": [
                -298.2851970410363,
                140.49316187635557
              ],
              "73301": [
                -84.3638387523945,
                -98.36046907666432
              ],
              "73302": [
                -52.97906022146467,
                304.029837029097
              ],
              "73303": [
                -22.268107316140842,
                -123.64221983670166
              ],
              "73304": [
                -110.31396869968435,
                308.37424680725013
              ],
              "73305": [
                136.4355614433944,
                35.88858733167305
              ],
              "73306": [
                11.427568929349272,
                -90.23985848235833
              ],
              "73307": [
                -80.9611030012338,
                325.60490329487493
              ],
              "73308": [
                -263.37996687123655,
                8.84969224865791
              ],
              "73309": [
                88.54261120393461,
                1.3354201628418145
              ],
              "73310": [
                58.757333659283475,
                -9.974015877426307
              ],
              "73311": [
                -163.5259977941409,
                315.30442435814615
              ],
              "73312": [
                -217.83174430668012,
                238.50559551407142
              ],
              "73313": [
                -149.29649847223502,
                12.118298805221078
              ],
              "73314": [
                -319.11457639126104,
                203.36929335931197
              ],
              "73315": [
                -201.6583954947528,
                44.87030839554039
              ],
              "73316": [
                -41.06724861385363,
                184.77778508960068
              ],
              "73317": [
                -274.8268497709235,
                49.08467168702912
              ],
              "73318": [
                39.6800828616615,
                247.96447211935495
              ],
              "73319": [
                -76.22834578872317,
                -68.65836162985364
              ],
              "73320": [
                41.52727124026887,
                -86.13853082732007
              ],
              "73321": [
                109.36331600305104,
                30.796819341751412
              ],
              "73322": [
                -262.4651167352511,
                96.90223836333047
              ],
              "73407": [
                314.34202092262217,
                -325.85655207312294
              ],
              "73408": [
                246.75805675761825,
                -307.9799989510507
              ],
              "73409": [
                415.66039051446006,
                -552.3837458463507
              ],
              "73410": [
                281.8191378912758,
                -262.0852580401783
              ],
              "73411": [
                183.11009830035601,
                -416.5912956660461
              ],
              "73412": [
                457.97501854799276,
                -482.54867563162514
              ],
              "73413": [
                275.2472382894599,
                -328.90332029106645
              ],
              "73414": [
                349.0261289544442,
                -291.2926290940005
              ],
              "73415": [
                397.5196840465033,
                -421.05591687260284
              ],
              "73416": [
                329.29268530787147,
                -537.3278958514813
              ],
              "73417": [
                374.0806005906773,
                -554.7672619410852
              ],
              "73418": [
                455.5411496256274,
                -520.8680736521613
              ],
              "73419": [
                206.25015832747582,
                -412.1350765057795
              ],
              "73420": [
                343.0624292245469,
                -237.34381210172614
              ],
              "73421": [
                238.85775036799646,
                -372.27892476597043
              ],
              "73422": [
                441.8115042716404,
                -363.48504286093714
              ],
              "73423": [
                411.28024299457115,
                -313.62188016487676
              ],
              "73424": [
                317.44870241690944,
                -292.4838058067516
              ],
              "73425": [
                278.1537951841583,
                -297.61964547318684
              ],
              "73426": [
                412.62696367792347,
                -356.6409215979892
              ],
              "73427": [
                417.04880604924006,
                -505.8242914999864
              ],
              "73428": [
                443.07958026053393,
                -334.25680270675036
              ],
              "73429": [
                402.5941401117933,
                -377.0192763194192
              ],
              "73430": [
                448.5372677867196,
                -531.8594819599164
              ],
              "73431": [
                479.53855534522256,
                -429.02735296984946
              ],
              "73432": [
                230.72493607622715,
                -345.27291207575024
              ],
              "73433": [
                302.8940170335899,
                -245.84919793091737
              ],
              "74462": [
                -138.3723571612199,
                216.9784400638013
              ],
              "75603": [
                -6.640329362729432,
                -100.36369329441237
              ],
              "75604": [
                -82.55540432136165,
                169.22608645685915
              ],
              "75605": [
                23.272744620428725,
                27.352113583421797
              ],
              "75858": [
                -178.08659804974297,
                254.79270119630948
              ],
              "75859": [
                -107.56518959710772,
                341.8536611689337
              ],
              "75860": [
                -307.4395893282683,
                198.5556113891284
              ],
              "76396": [
                56.60314573295874,
                180.69612876664686
              ],
              "77853": [
                211.54090456533348,
                -375.11260893108516
              ],
              "77854": [
                307.46437143158016,
                -339.0624518185987
              ],
              "77855": [
                380.5809479440441,
                -529.7595801588758
              ],
              "77856": [
                248.2231244287441,
                -424.1203572694208
              ],
              "77857": [
                310.8532375596579,
                -364.93707763697995
              ],
              "77858": [
                481.530145429035,
                -445.9029403639488
              ],
              "77859": [
                394.72891426459114,
                -519.3306945577235
              ],
              "77860": [
                414.53482287387044,
                -383.74423348611106
              ],
              "78452": [
                36.420268455036904,
                -74.69486120028567
              ],
              "78453": [
                -216.03282066432573,
                82.03723258861596
              ],
              "78454": [
                122.08872229573275,
                2.101192300589201
              ],
              "78470": [
                217.2007327825672,
                -391.36394983755
              ],
              "78471": [
                234.83800701880435,
                -224.84891165248746
              ],
              "78472": [
                362.48988914945687,
                -520.3758087034431
              ],
              "78473": [
                246.81642805248165,
                -339.4090083293856
              ],
              "78474": [
                324.386423680853,
                -248.5121345352622
              ],
              "79304": [
                -255.7659914818331,
                266.3446356794135
              ]
            },
            "frozen": true
          }
        },
        {
          "title": "Problem10",
          "query": "MATCH PATH=(p:Airport)-[:BEGIN_ROUTE]->(o:Route)-[:END_ROUTE]->(p1:Airport)\nWITH *, point({ longitude: p.Longitude, latitude: p.Latitude }) AS source, point({ longitude: p1.Longitude, latitude: p1.Latitude }) AS destination\nWHERE o.AirlineID IS NOT NULL AND p.City = \"Seattle\"\nRETURN PATH, round(distance(source, destination))/1000 AS travelDistance, p.City, p.Name, p1.City, p1.Name, o.Stops, o.AirlineID\nORDER BY travelDistance ASC",
          "width": 11,
          "height": 2,
          "x": 0,
          "y": 11,
          "type": "table",
          "selection": {},
          "settings": {
            "nodePositions": {}
          }
        }
      ]
    }
  ],
  "parameters": {}
}